keep/__init__.py
keep/about.py
keep/cli.py
keep/utils.py
keep/commands/__init__.py
keep/commands/cmd_completion.py
keep/commands/cmd_edit.py
keep/commands/cmd_github_token.py
keep/commands/cmd_grep.py
keep/commands/cmd_init.py
keep/commands/cmd_list.py
keep/commands/cmd_new.py
keep/commands/cmd_pull.py
keep/commands/cmd_push.py
keep/commands/cmd_rm.py
keep/commands/cmd_run.py
keep/commands/cmd_update.py
keep/legacy_commands/removed_cmd_pull.py
keep/legacy_commands/removed_cmd_push.py
keep/legacy_commands/removed_cmd_register.py
keep-2.11.dist-info/entry_points.txt
keep-2.11.dist-info/WHEEL
keep-2.11.dist-info/METADATA
keep-2.11.dist-info/RECORD
