Metadata-Version: 2.1
Name: keep
Version: 2.11
Summary: Personal shell command keeper
Author-email: Himanshu Mishra <himanshu.mishra.kgp@gmail.com>
Requires-Python: >=3.8
Requires-Dist: PyGithub
Requires-Dist: click
Requires-Dist: requests
Requires-Dist: terminaltables3
Project-URL: Downloads, https://github.com/orkohunter/keep/archive/master.zip
Project-URL: Homepage, https://github.com/orkohunter/keep
